mrtproto/__init__.py
mrtproto/__init__.pyi
mrtproto/autopilot_pb2.py
mrtproto/autopilot_pb2.pyi
mrtproto/radar_pb2.py
mrtproto/radar_pb2.pyi
mrtproto/sensor_pb2.py
mrtproto/sensor_pb2.pyi
mrtproto/vision_pb2.py
mrtproto/vision_pb2.pyi
mrtproto-21.88.dist-info/METADATA
mrtproto-21.88.dist-info/WHEEL
mrtproto-21.88.dist-info/top_level.txt
mrtproto-21.88.dist-info/RECORD
