Metadata-Version: 2.1
Name: mrtproto
Version: 21.88
Summary: Communicate with the MRT Autopilot Protobuf API
Maintainer-email: Nathan Knotts <nathan@magothyrt.com>
Requires-Python: >=3.8
Requires-Dist: wheel
Requires-Dist: protobuf
